aiovault/__init__.py
aiovault/audit.py
aiovault/auth.py
aiovault/base.py
aiovault/client.py
aiovault/exceptions.py
aiovault/policy.py
aiovault/secrets.py
aiovault/vault_sys.py
aiovault-1.1.1.dist-info/DESCRIPTION.rst
aiovault-1.1.1.dist-info/METADATA
aiovault-1.1.1.dist-info/RECORD
aiovault-1.1.1.dist-info/WHEEL
aiovault-1.1.1.dist-info/metadata.json
aiovault-1.1.1.dist-info/top_level.txt
