Metadata-Version: 2.0
Name: aiovault
Version: 1.1.1
Summary: Vault asyncio
Home-page: https://github.com/terrycain/aiovault
Author: Terry Cain
Author-email: terry@terrys-home.co.uk
License: GNU General Public License v3
Keywords: aiovault
Platform: UNKNOWN
Classifier: Development Status :: 2 - Pre-Alpha
Classifier: Intended Audience :: Developers
Classifier: License :: OSI Approved :: GNU General Public License v3 (GPLv3)
Classifier: Natural Language :: English
Classifier: Programming Language :: Python :: 3
Classifier: Programming Language :: Python :: 3.5
Classifier: Programming Language :: Python :: 3.6
Requires-Dist: aiohttp
Requires-Dist: python-dateutil
